turu/mysql/__init__.py
turu/mysql/async_connection.py
turu/mysql/async_cursor.py
turu/mysql/connection.py
turu/mysql/cursor.py
turu/mysql/mock_async_connection.py
turu/mysql/mock_async_cursor.py
turu/mysql/mock_connection.py
turu/mysql/mock_cursor.py
turu/mysql/py.typed
turu_mysql-0.13.2.dist-info/METADATA
turu_mysql-0.13.2.dist-info/WHEEL
turu_mysql-0.13.2.dist-info/RECORD
